<?xml version="1.0" encoding="utf-8"?>
<Component Name="/UI2/ADAPTATION_PAGE" ConfId="Z53195D96193B19B5E5F89F800CC8FC9" ConfType="07" ConfVar="" ChangedBy="UI2">
 <Node Name="CONFIGURATION_CONTEXT" SimpleFormat="true">
  <Item Index="000001" SimpleFormat="true">
   <Node Name="PAGE" SimpleFormat="true">
    <Item Index="000001" SimpleFormat="true">
     <ID>X-SAP-UI2-CATALOGPAGE:zebdgs_export_xls</ID>
     <Node Name="GADGET_USAGE" SimpleFormat="true">
      <Item Index="000001" SimpleFormat="true">
       <USAGE_ID Final="5 ">00O2TJUBTY8W66MZYK1KFWV4Y</USAGE_ID>
      </Item>
     </Node>
    </Item>
   </Node>
  </Item>
 </Node>
</Component>
